Workbook

Sheet Basic
A1: Order ID | B1: Product | C1: Price per unit | D1: Quantity | E1: Total Amount (Relative) | F1: % Total | H1: Fungsi | I1: Deskripsi | J1: Hasil | K1: Formula
A2: 1001 | B2: Laptop | C2: 4612059 | D2: 20 | E2: =C2*D2 -> 92241180 | F2: =E2/$E$12 -> 0.195731 | H2: SUM | I2: Menjumlahkan nilai dalam rentang tertentu | J2: =SUM(D2:D11) -> 121 | K2: =_xlfn.FORMULATEXT(J2) -> =SUM(D2:D11)
A3: 1002 | B3: Mouse | C3: 4156127 | D3: 1 | E3: =C3*D3 -> 4156127 | F3: =E3/$E$12 -> 0.0088190861 | H3: AVERAGE | I3: Menghitung rata-rata nilai | J3: =AVERAGE(D2:D11) -> 12.1 | K3: =_xlfn.FORMULATEXT(J3) -> =AVERAGE(D2:D11)
A4: 1003 | B4: Printer | C4: 1725042 | D4: 17 | E4: =C4*D4 -> 29325714 | F4: =E4/$E$12 -> 0.062227645 | H4: COUNT | I4: Menghitung jumlah sel yang berisi angka | J4: =COUNT(D2:D11) -> 10 | K4: =_xlfn.FORMULATEXT(J4) -> =COUNT(D2:D11)
A5: 1004 | B5: Laptop | C5: 4612059 | D5: 12 | E5: =C5*D5 -> 55344708 | F5: =E5/$E$12 -> 0.1174386 | H5: COUNTA | I5: Menghitung jumlah sel yang tidak kosong/text | J5: =COUNTA(D2:D11) -> 10 | K5: =_xlfn.FORMULATEXT(J5) -> =COUNTA(D2:D11)
A6: 1005 | B6: Headphones | C6: 381259 | D6: 9 | E6: =C6*D6 -> 3431331 | F6: =E6/$E$12 -> 0.0072811065 | H6: MAX | I6: Mencari nilai maksimum dalam rentang | J6: =MAX(C2:C11) -> 9154155 | K6: =_xlfn.FORMULATEXT(J6) -> =MAX(C2:C11)
A7: 1006 | B7: Tablet | C7: 3517798 | D7: 5 | E7: =C7*D7 -> 17588990 | F7: =E7/$E$12 -> 0.037322925 | H7: MIN | I7: Mencari nilai minimum dalam rentang | J7: =MIN(C2:C11) -> 381259 | K7: =_xlfn.FORMULATEXT(J7) -> =MIN(C2:C11)
A8: 1007 | B8: Printer | C8: 4056860 | D8: 9 | E8: =C8*D8 -> 36511740 | F8: =E8/$E$12 -> 0.07747602 | H8: MEDIAN | I8: Menghitung nilai tengah dari data numerik | J8: =MEDIAN(D2:D11) -> 12 | K8: =_xlfn.FORMULATEXT(J8) -> =MEDIAN(D2:D11)
A9: 1008 | B9: Smartphone | C9: 9154155 | D9: 12 | E9: =C9*D9 -> 109849860 | F9: =E9/$E$12 -> 0.23309571 | H9: MODE | I9: Menemukan nilai yang paling sering muncul | J9: =MODE(D2:D11) -> 20 | K9: =_xlfn.FORMULATEXT(J9) -> =MODE(D2:D11)
A10: 1009 | B10: Camera | C10: 4734466 | D10: 16 | E10: =C10*D10 -> 75751456 | F10: =E10/$E$12 -> 0.16074066 | H10: PRODUCT | I10: Menghitung hasil perkalian semua nilai | J10: =PRODUCT(D2:D11) -> 6345216000 | K10: =_xlfn.FORMULATEXT(J10) -> =PRODUCT(D2:D11)
A11: 1010 | B11: Headphones | C11: 2353197 | D11: 20 | E11: =C11*D11 -> 47063940 | F11: =E11/$E$12 -> 0.099867241
E12: =SUM(E2:E11) -> 471265046 | F12: =SUM(F2:F11) -> 1
A15: Qty Sold | B15: Q1 | C15: Q2 | D15: Q3 | E15: Q4 | F15: Total | G15: % Total
A16: Laptop | B16: 20 | C16: 30 | D16: 15 | E16: 65 | F16: =SUM(B16:E16) -> 130 | G16: =F16/$F$19 -> 0.12633625
A17: Mouse | B17: 127 | C17: 135 | D17: 129 | E17: 165 | F17: =SUM(B17:E17) -> 556 | G17: =F17/$F$19 -> 0.54033042
A18: Printer | B18: 87 | C18: 96 | D18: 85 | E18: 75 | F18: =SUM(B18:E18) -> 343 | G18: =F18/$F$19 -> 0.33333333
A19: Total | B19: =SUM(B16:B18) -> 234 | C19: =SUM(C16:C18) -> 261 | D19: =SUM(D16:D18) -> 229 | E19: =SUM(E16:E18) -> 305 | F19: =SUM(F16:F18) -> 1029 | G19: =SUM(G16:G18) -> 1
A21: % penjualan per product per quarter dalam 1 tahun
A22: Qty Sold | B22: Q1 | C22: Q2 | D22: Q3 | E22: Q4
A23: Laptop | B23: =B16/$F16 -> 0.15384615 | C23: =C16/$F16 -> 0.23076923 | D23: =D16/$F16 -> 0.11538462 | E23: =E16/$F16 -> 0.5
A24: Mouse | B24: =B17/$F17 -> 0.22841727 | C24: =C17/$F17 -> 0.24280576 | D24: =D17/$F17 -> 0.23201439 | E24: =E17/$F17 -> 0.29676259
A25: Printer | B25: =B18/$F18 -> 0.25364431 | C25: =C18/$F18 -> 0.27988338 | D25: =D18/$F18 -> 0.24781341 | E25: =E18/$F18 -> 0.21865889
A26: Total | B26: =SUM(B23:B25) -> 0.63590773 | C26: =SUM(C23:C25) -> 0.75345837 | D26: =SUM(D23:D25) -> 0.59521241 | E26: =SUM(E23:E25) -> 1.0154215
A28: % penjualan per product per quarter dalam 1 tahun (ALL Product)
A29: Qty Sold | B29: Q1 | C29: Q2 | D29: Q3 | E29: Q4 | F29: Total
A30: Laptop | B30: =B16/$F$19 -> 0.019436346 | C30: =C16/$F$19 -> 0.029154519 | D30: =D16/$F$19 -> 0.014577259 | E30: =E16/$F$19 -> 0.063168124 | F30: =SUM(B30:E32) -> 1
A31: Mouse | B31: =B17/$F$19 -> 0.1234208 | C31: =C17/$F$19 -> 0.13119534 | D31: =D17/$F$19 -> 0.12536443 | E31: =E17/$F$19 -> 0.16034985
A32: Printer | B32: =B18/$F$19 -> 0.084548105 | C32: =C18/$F$19 -> 0.093294461 | D32: =D18/$F$19 -> 0.08260447 | E32: =E18/$F$19 -> 0.072886297
A33: Insight: Penjualan terbaik adalah mouse pada Q4

Sheet Logical,CondAggFunction
A1: Order ID | B1: Sales Name | C1: Region | D1: Product | E1: Item Price | F1: Discount | G1: Quantity | H1: Total Amount | I1: Customer Segment | J1: Shipping Cost | K1: Delivery Time (Days) | L1: Order Category | M1: Delivery Category (Nested IF) | N1: Delivery Category (IFS) | O1: AND | P1: OR | Q1: NOT
A2: 1001 | B2: Bob Martin | C2: North | D2: Laptop | E2: 4612059 | F2: 0.1 | G2: 20 | H2: =E2*G2 -> 92241180 | I2: Corporate | J2: 327163 | K2: 2 | L2: =IF(G2>=10,"Bulk Order","Retail") -> Bulk Order | M2: =IF(K2<=5,"Fast Delivery",IF(K2<=10,"Standard Delivery","Slow Delivery")) -> Fast Delivery | N2: =_xlfn.IFS(K2<=5,"Fast Delivery",K2<=10,"Standard Delivery",K2>10,"Slow Delivery") -> Fast Delivery | O2: =IF(AND(K2<=5,J2>500000),"High Priority Shipping","Standard Shipping") -> Standard Shipping | P2: =IF(OR(D2="Laptop",D2="Tablet"),"Premium Product","Reguler Product") -> Premium Product | Q2: =IF(NOT(I2="Consumer"),"Business Order","Consumer Order") -> Business Order
A3: 1002 | B3: Bob Martin | C3: North | D3: Mouse | E3: 415612 | F3: 0.17 | G3: 1 | H3: =E3*G3 -> 415612 | I3: Consumer | J3: 783312 | K3: 7 | L3: =IF(G3>=10,"Bulk Order","Retail") -> Retail | M3: =IF(K3<=5,"Fast Delivery",IF(K3<=10,"Standard Delivery","Slow Delivery")) -> Standard Delivery | N3: =_xlfn.IFS(K3<=5,"Fast Delivery",K3<=10,"Standard Delivery",K3>10,"Slow Delivery") -> Standard Delivery | O3: =IF(AND(K3<=5,J3>500000),"High Priority Shipping","Standard Shipping") -> Standard Shipping | P3: =IF(OR(D3="Laptop",D3="Tablet"),"Premium Product","Reguler Product") -> Reguler Product | Q3: =IF(NOT(I3="Consumer"),"Business Order","Consumer Order") -> Consumer Order
A4: 1003 | B4: David White | C4: East | D4: Printer | E4: 1725042 | F4: 0.2 | G4: 17 | H4: =E4*G4 -> 29325714 | I4: Small Business | J4: 573976 | K4: 7 | L4: =IF(G4>=10,"Bulk Order","Retail") -> Bulk Order | M4: =IF(K4<=5,"Fast Delivery",IF(K4<=10,"Standard Delivery","Slow Delivery")) -> Standard Delivery | N4: =_xlfn.IFS(K4<=5,"Fast Delivery",K4<=10,"Standard Delivery",K4>10,"Slow Delivery") -> Standard Delivery | O4: =IF(AND(K4<=5,J4>500000),"High Priority Shipping","Standard Shipping") -> Standard Shipping | P4: =IF(OR(D4="Laptop",D4="Tablet"),"Premium Product","Reguler Product") -> Reguler Product | Q4: =IF(NOT(I4="Consumer"),"Business Order","Consumer Order") -> Business Order
A5: 1004 | B5: Bob Martin | C5: East | D5: Laptop | E5: 32495820 | F5: 0.19 | G5: 12 | H5: =E5*G5 -> 389949840 | I5: Small Business | J5: 715388 | K5: 8 | L5: =IF(G5>=10,"Bulk Order","Retail") -> Bulk Order | M5: =IF(K5<=5,"Fast Delivery",IF(K5<=10,"Standard Delivery","Slow Delivery")) -> Standard Delivery | N5: =_xlfn.IFS(K5<=5,"Fast Delivery",K5<=10,"Standard Delivery",K5>10,"Slow Delivery") -> Standard Delivery | O5: =IF(AND(K5<=5,J5>500000),"High Priority Shipping","Standard Shipping") -> Standard Shipping | P5: =IF(OR(D5="Laptop",D5="Tablet"),"Premium Product","Reguler Product") -> Premium Product | Q5: =IF(NOT(I5="Consumer"),"Business Order","Consumer Order") -> Business Order
A6: 1005 | B6: Eve Smith | C6: West | D6: Headphones | E6: 381259 | F6: 0.08 | G6: 9 | H6: =E6*G6 -> 3431331 | I6: Consumer | J6: 516373 | K6: 1 | L6: =IF(G6>=10,"Bulk Order","Retail") -> Retail | M6: =IF(K6<=5,"Fast Delivery",IF(K6<=10,"Standard Delivery","Slow Delivery")) -> Fast Delivery | N6: =_xlfn.IFS(K6<=5,"Fast Delivery",K6<=10,"Standard Delivery",K6>10,"Slow Delivery") -> Fast Delivery | O6: =IF(AND(K6<=5,J6>500000),"High Priority Shipping","Standard Shipping") -> High Priority Shipping | P6: =IF(OR(D6="Laptop",D6="Tablet"),"Premium Product","Reguler Product") -> Reguler Product | Q6: =IF(NOT(I6="Consumer"),"Business Order","Consumer Order") -> Consumer Order
A7: 1006 | B7: Bob Martin | C7: South | D7: Tablet | E7: 3517798 | F7: 0.08 | G7: 5 | H7: =E7*G7 -> 17588990 | I7: Corporate | J7: 488560 | K7: 4 | L7: =IF(G7>=10,"Bulk Order","Retail") -> Retail | M7: =IF(K7<=5,"Fast Delivery",IF(K7<=10,"Standard Delivery","Slow Delivery")) -> Fast Delivery | N7: =_xlfn.IFS(K7<=5,"Fast Delivery",K7<=10,"Standard Delivery",K7>10,"Slow Delivery") -> Fast Delivery | O7: =IF(AND(K7<=5,J7>500000),"High Priority Shipping","Standard Shipping") -> Standard Shipping | P7: =IF(OR(D7="Laptop",D7="Tablet"),"Premium Product","Reguler Product") -> Premium Product | Q7: =IF(NOT(I7="Consumer"),"Business Order","Consumer Order") -> Business Order
A8: 1007 | B8: Bob Martin | C8: East | D8: Printer | E8: 4056860 | F8: 0.14 | G8: 9 | H8: =E8*G8 -> 36511740 | I8: Corporate | J8: 541297 | K8: 6 | L8: =IF(G8>=10,"Bulk Order","Retail") -> Retail | M8: =IF(K8<=5,"Fast Delivery",IF(K8<=10,"Standard Delivery","Slow Delivery")) -> Standard Delivery | N8: =_xlfn.IFS(K8<=5,"Fast Delivery",K8<=10,"Standard Delivery",K8>10,"Slow Delivery") -> Standard Delivery | O8: =IF(AND(K8<=5,J8>500000),"High Priority Shipping","Standard Shipping") -> Standard Shipping | P8: =IF(OR(D8="Laptop",D8="Tablet"),"Premium Product","Reguler Product") -> Reguler Product | Q8: =IF(NOT(I8="Consumer"),"Business Order","Consumer Order") -> Business Order
A9: 1008 | B9: David White | C9: East | D9: Smartphone | E9: 9154155 | F9: 0.2 | G9: 12 | H9: =E9*G9 -> 109849860 | I9: Consumer | J9: 568288 | K9: 7 | L9: =IF(G9>=10,"Bulk Order","Retail") -> Bulk Order | M9: =IF(K9<=5,"Fast Delivery",IF(K9<=10,"Standard Delivery","Slow Delivery")) -> Standard Delivery | N9: =_xlfn.IFS(K9<=5,"Fast Delivery",K9<=10,"Standard Delivery",K9>10,"Slow Delivery") -> Standard Delivery | O9: =IF(AND(K9<=5,J9>500000),"High Priority Shipping","Standard Shipping") -> Standard Shipping | P9: =IF(OR(D9="Laptop",D9="Tablet"),"Premium Product","Reguler Product") -> Reguler Product | Q9: =IF(NOT(I9="Consumer"),"Business Order","Consumer Order") -> Consumer Order
A10: 1009 | B10: Alice Johnson | C10: East | D10: Camera | E10: 4734466 | F10: 0.16 | G10: 16 | H10: =E10*G10 -> 75751456 | I10: Consumer | J10: 652076 | K10: 13 | L10: =IF(G10>=10,"Bulk Order","Retail") -> Bulk Order | M10: =IF(K10<=5,"Fast Delivery",IF(K10<=10,"Standard Delivery","Slow Delivery")) -> Slow Delivery | N10: =_xlfn.IFS(K10<=5,"Fast Delivery",K10<=10,"Standard Delivery",K10>10,"Slow Delivery") -> Slow Delivery | O10: =IF(AND(K10<=5,J10>500000),"High Priority Shipping","Standard Shipping") -> Standard Shipping | P10: =IF(OR(D10="Laptop",D10="Tablet"),"Premium Product","Reguler Product") -> Reguler Product | Q10: =IF(NOT(I10="Consumer"),"Business Order","Consumer Order") -> Consumer Order
A11: 1010 | B11: Charlie Brown | C11: East | D11: Headphones | E11: 235319 | F11: 0.14 | G11: 20 | H11: =E11*G11 -> 4706380 | I11: Corporate | J11: 394800 | K11: 2 | L11: =IF(G11>=10,"Bulk Order","Retail") -> Bulk Order | M11: =IF(K11<=5,"Fast Delivery",IF(K11<=10,"Standard Delivery","Slow Delivery")) -> Fast Delivery | N11: =_xlfn.IFS(K11<=5,"Fast Delivery",K11<=10,"Standard Delivery",K11>10,"Slow Delivery") -> Fast Delivery | O11: =IF(AND(K11<=5,J11>500000),"High Priority Shipping","Standard Shipping") -> Standard Shipping | P11: =IF(OR(D11="Laptop",D11="Tablet"),"Premium Product","Reguler Product") -> Reguler Product | Q11: =IF(NOT(I11="Consumer"),"Business Order","Consumer Order") -> Business Order
A12: 1011 | B12: Alice Johnson | C12: West | D12: Tablet | E12: 14931496 | F12: 0.11 | G12: 14 | H12: =E12*G12 -> 209040944 | I12: Small Business | J12: 660012 | K12: 4 | L12: =IF(G12>=10,"Bulk Order","Retail") -> Bulk Order | M12: =IF(K12<=5,"Fast Delivery",IF(K12<=10,"Standard Delivery","Slow Delivery")) -> Fast Delivery | N12: =_xlfn.IFS(K12<=5,"Fast Delivery",K12<=10,"Standard Delivery",K12>10,"Slow Delivery") -> Fast Delivery | O12: =IF(AND(K12<=5,J12>500000),"High Priority Shipping","Standard Shipping") -> High Priority Shipping | P12: =IF(OR(D12="Laptop",D12="Tablet"),"Premium Product","Reguler Product") -> Premium Product | Q12: =IF(NOT(I12="Consumer"),"Business Order","Consumer Order") -> Business Order
A13: 1012 | B13: Charlie Brown | C13: West | D13: Headphones | E13: 265689 | F13: 0.08 | G13: 9 | H13: =E13*G13 -> 2391201 | I13: Small Business | J13: 609492 | K13: 3 | L13: =IF(G13>=10,"Bulk Order","Retail") -> Retail | M13: =IF(K13<=5,"Fast Delivery",IF(K13<=10,"Standard Delivery","Slow Delivery")) -> Fast Delivery | N13: =_xlfn.IFS(K13<=5,"Fast Delivery",K13<=10,"Standard Delivery",K13>10,"Slow Delivery") -> Fast Delivery | O13: =IF(AND(K13<=5,J13>500000),"High Priority Shipping","Standard Shipping") -> High Priority Shipping | P13: =IF(OR(D13="Laptop",D13="Tablet"),"Premium Product","Reguler Product") -> Reguler Product | Q13: =IF(NOT(I13="Consumer"),"Business Order","Consumer Order") -> Business Order
... A31: 1030 | B31: Charlie Brown | C31: South | D31: Chair | E31: 1622550 | F31: 0.15 | G31: 14 | H31: =E31*G31 -> 22715700 | I31: Consumer | J31: 414403 | K31: 3 | L31: =IF(G31>=10,"Bulk Order","Retail") -> Bulk Order | M31: =IF(K31<=5,"Fast Delivery",IF(K31<=10,"Standard Delivery","Slow Delivery")) -> Fast Delivery | N31: =_xlfn.IFS(K31<=5,"Fast Delivery",K31<=10,"Standard Delivery",K31>10,"Slow Delivery") -> Fast Delivery | O31: =IF(AND(K31<=5,J31>500000),"High Priority Shipping","Standard Shipping") -> Standard Shipping | P31: =IF(OR(D31="Laptop",D31="Tablet"),"Premium Product","Reguler Product") -> Reguler Product | Q31: =IF(NOT(I31="Consumer"),"Business Order","Consumer Order") -> Consumer Order
A33: SOAL:
A34: IF, IFS, Nested IF | M34: SUMIF
A35: IF | B35: Jika Qty >= 10 maka Bulk Order, Retail | M35: Laptop | N35: =SUMIF($D$2:$D$31,M35,$H$2:$H$31) -> 1167551318
A36: Nested IF | B36: Jika Delivery <=5 hari maka Fast Delivery, 6-10 Standard Delivery,>10 Slow Delivery | M36: Mouse | N36: =SUMIF($D$2:$D$31,M36,$H$2:$H$31) -> 6524844
A37: IFS | B37: Jika Delivery <=5 hari maka Fast Delivery, 6-10 Standard Delivery,>10 Slow Delivery | M37: Printer | N37: =SUMIF($D$2:$D$31,M37,$H$2:$H$31) -> 75702617
A38: AND
A39: Jika Delivery Time (Days) <= 5 dan Shipping Cost > 500,000, maka itu dianggap "High Priority Shipping", jika tidak "Standard Shipping" | M39: SUMIFS
M40: Laptop | N40: Corporate | O40: =SUMIFS(H2:H31,D2:D31,M40,I2:I31,N40) -> 471010554 | P40: =_xlfn.FORMULATEXT(O40) -> =SUMIFS(H2:H31;D2:D31;M40;I2:I31;N40)
A41: OR
A42: Jika Product adalah "Laptop" atau "Tablet", maka produk dianggap "Premium Product", jika tidak "Regular Product" | M42: COUNTIF | N42: Jumlah invoice atau orderan yang masuk
M43: Laptop | N43: =COUNTIF($D$2:$D$31,M43) -> 5
A44: NOT | M44: Mouse | N44: =COUNTIF($D$2:$D$31,M44) -> 4
A45: Jika Customer Segment BUKAN "Consumer", maka tampilkan "Business Order", jika tidak "Consumer Order". | M45: Printer | N45: =COUNTIF($D$2:$D$31,M45) -> 3
M47: COUNTIFS
M48: Laptop | N48: Corporate | O48: =COUNTIFS(D2:D31,M48,I2:I31,N48) -> 2
M50: AVERAGEIF | N50: Rata-rata penjualan produk perbulannya
M51: Laptop | N51: =AVERAGEIF($D$2:$D$31,M51,$G$2:$G$31) -> 12.8
M52: Mouse | N52: =AVERAGEIF($D$2:$D$31,M52,$G$2:$G$31) -> 4.75
M53: Printer | N53: =AVERAGEIF($D$2:$D$31,M53,$G$2:$G$31) -> 12.333333
M55: AVERAGEIFS
M56: Laptop | N56: Corporate | O56: =AVERAGEIFS(G2:G31,D2:D31,M56,I2:I31,N56) -> 19

Sheet Lookup
A1: Order ID | B1: Sales Name | C1: Region | D1: Product | E1: Item Price | F1: Discount | G1: Quantity | H1: Customer Segment | I1: Shipping Cost | J1: Delivery Time (Days) | K1: Product Category (VLOOKUP) | L1: Warehouse (VLOOKUP) | M1: Stock Available (HLOOKUP) | N1: Reorder Level (XLOOKUP) | O1: Supplier (INDEX-MATCH)
A2: 1001 | B2: Bob Martin | C2: North | D2: Laptop | E2: 4612059 | F2: 0.1 | G2: 20 | H2: Corporate | I2: 327163 | J2: 2 | K2: =VLOOKUP(D2,LookupTable!$B$2:$C$11,2,FALSE) -> Technology | L2: =VLOOKUP(D2,LookupTable!$B$2:$G$11,6,FALSE) -> Warehouse 1 | M2: =HLOOKUP(D2,LookupTable!$A$15:$K$19,4,FALSE) -> 50 | N2: Fungsi Xlookup tidak ada (Excel belum support) | O2: =INDEX(LookupTable!$D$2:$D$11,MATCH(Lookup!D2,LookupTable!$B$2:$B$11,0)) -> Supplier A
A3: 1002 | B3: Bob Martin | C3: North | D3: Mouse | E3: 415612 | F3: 0.17 | G3: 1 | H3: Consumer | I3: 783312 | J3: 7 | K3: =VLOOKUP(D3,LookupTable!$B$2:$C$11,2,FALSE) -> Accessories | L3: =VLOOKUP(D3,LookupTable!$B$2:$G$11,6,FALSE) -> Warehouse 2 | M3: =HLOOKUP(D3,LookupTable!$A$15:$K$19,4,FALSE) -> 150 | O3: =INDEX(LookupTable!$D$2:$D$11,MATCH(Lookup!D3,LookupTable!$B$2:$B$11,0)) -> Supplier I
A4: 1003 | B4: David White | C4: East | D4: Printer | E4: 1725042 | F4: 0.2 | G4: 17 | H4: Small Business | I4: 573976 | J4: 7 | K4: =VLOOKUP(D4,LookupTable!$B$2:$C$11,2,FALSE) -> Technology | L4: =VLOOKUP(D4,LookupTable!$B$2:$G$11,6,FALSE) -> Warehouse 4 | M4: =HLOOKUP(D4,LookupTable!$A$15:$K$19,4,FALSE) -> 20 | O4: =INDEX(LookupTable!$D$2:$D$11,MATCH(Lookup!D4,LookupTable!$B$2:$B$11,0)) -> Supplier G
A5: 1004 | B5: Bob Martin | C5: East | D5: Laptop | E5: 32495820 | F5: 0.19 | G5: 12 | H5: Small Business | I5: 715388 | J5: 8 | K5: =VLOOKUP(D5,LookupTable!$B$2:$C$11,2,FALSE) -> Technology | L5: =VLOOKUP(D5,LookupTable!$B$2:$G$11,6,FALSE) -> Warehouse 1 | M5: =HLOOKUP(D5,LookupTable!$A$15:$K$19,4,FALSE) -> 50 | O5: =INDEX(LookupTable!$D$2:$D$11,MATCH(Lookup!D5,LookupTable!$B$2:$B$11,0)) -> Supplier A
A6: 1005 | B6: Eve Smith | C6: West | D6: Headphones | E6: 381259 | F6: 0.08 | G6: 9 | H6: Consumer | I6: 516373 | J6: 1 | K6: =VLOOKUP(D6,LookupTable!$B$2:$C$11,2,FALSE) -> Accessories | L6: =VLOOKUP(D6,LookupTable!$B$2:$G$11,6,FALSE) -> Warehouse 4 | M6: =HLOOKUP(D6,LookupTable!$A$15:$K$19,4,FALSE) -> 80 | O6: =INDEX(LookupTable!$D$2:$D$11,MATCH(Lookup!D6,LookupTable!$B$2:$B$11,0)) -> Supplier D
A7: 1006 | B7: Bob Martin | C7: South | D7: Tablet | E7: 3517798 | F7: 0.08 | G7: 5 | H7: Corporate | I7: 488560 | J7: 4 | K7: =VLOOKUP(D7,LookupTable!$B$2:$C$11,2,FALSE) -> Technology | L7: =VLOOKUP(D7,LookupTable!$B$2:$G$11,6,FALSE) -> Warehouse 3 | M7: =HLOOKUP(D7,LookupTable!$A$15:$K$19,4,FALSE) -> 30 | O7: =INDEX(LookupTable!$D$2:$D$11,MATCH(Lookup!D7,LookupTable!$B$2:$B$11,0)) -> Supplier C
A8: 1007 | B8: Bob Martin | C8: East | D8: Printer | E8: 4056860 | F8: 0.14 | G8: 9 | H8: Corporate | I8: 541297 | J8: 6 | K8: =VLOOKUP(D8,LookupTable!$B$2:$C$11,2,FALSE) -> Technology | L8: =VLOOKUP(D8,LookupTable!$B$2:$G$11,6,FALSE) -> Warehouse 4 | M8: =HLOOKUP(D8,LookupTable!$A$15:$K$19,4,FALSE) -> 20 | O8: =INDEX(LookupTable!$D$2:$D$11,MATCH(Lookup!D8,LookupTable!$B$2:$B$11,0)) -> Supplier G
A9: 1008 | B9: David White | C9: East | D9: Smartphone | E9: 9154155 | F9: 0.2 | G9: 12 | H9: Consumer | I9: 568288 | J9: 7 | K9: =VLOOKUP(D9,LookupTable!$B$2:$C$11,2,FALSE) -> Technology | L9: =VLOOKUP(D9,LookupTable!$B$2:$G$11,6,FALSE) -> Warehouse 2 | M9: =HLOOKUP(D9,LookupTable!$A$15:$K$19,4,FALSE) -> 30 | O9: =INDEX(LookupTable!$D$2:$D$11,MATCH(Lookup!D9,LookupTable!$B$2:$B$11,0)) -> Supplier B
A10: 1009 | B10: Alice Johnson | C10: East | D10: Camera | E10: 4734466 | F10: 0.16 | G10: 16 | H10: Consumer | I10: 652076 | J10: 13 | K10: =VLOOKUP(D10,LookupTable!$B$2:$C$11,2,FALSE) -> Electronics | L10: =VLOOKUP(D10,LookupTable!$B$2:$G$11,6,FALSE) -> Warehouse 1 | M10: =HLOOKUP(D10,LookupTable!$A$15:$K$19,4,FALSE) -> 10 | O10: =INDEX(LookupTable!$D$2:$D$11,MATCH(Lookup!D10,LookupTable!$B$2:$B$11,0)) -> Supplier H
A11: 1010 | B11: Charlie Brown | C11: East | D11: Headphones | E11: 235319 | F11: 0.14 | G11: 20 | H11: Corporate | I11: 394800 | J11: 2 | K11: =VLOOKUP(D11,LookupTable!$B$2:$C$11,2,FALSE) -> Accessories | L11: =VLOOKUP(D11,LookupTable!$B$2:$G$11,6,FALSE) -> Warehouse 4 | M11: =HLOOKUP(D11,LookupTable!$A$15:$K$19,4,FALSE) -> 80 | O11: =INDEX(LookupTable!$D$2:$D$11,MATCH(Lookup!D11,LookupTable!$B$2:$B$11,0)) -> Supplier D
A12: 1011 | B12: Alice Johnson | C12: West | D12: Tablet | E12: 14931496 | F12: 0.11 | G12: 14 | H12: Small Business | I12: 660012 | J12: 4 | K12: =VLOOKUP(D12,LookupTable!$B$2:$C$11,2,FALSE) -> Technology | L12: =VLOOKUP(D12,LookupTable!$B$2:$G$11,6,FALSE) -> Warehouse 3 | M12: =HLOOKUP(D12,LookupTable!$A$15:$K$19,4,FALSE) -> 30 | O12: =INDEX(LookupTable!$D$2:$D$11,MATCH(Lookup!D12,LookupTable!$B$2:$B$11,0)) -> Supplier C
A13: 1012 | B13: Charlie Brown | C13: West | D13: Headphones | E13: 265689 | F13: 0.08 | G13: 9 | H13: Small Business | I13: 609492 | J13: 3 | K13: =VLOOKUP(D13,LookupTable!$B$2:$C$11,2,FALSE) -> Accessories | L13: =VLOOKUP(D13,LookupTable!$B$2:$G$11,6,FALSE) -> Warehouse 4 | M13: =HLOOKUP(D13,LookupTable!$A$15:$K$19,4,FALSE) -> 80 | O13: =INDEX(LookupTable!$D$2:$D$11,MATCH(Lookup!D13,LookupTable!$B$2:$B$11,0)) -> Supplier D
A14: 1013 | B14: David White | C14: East | D14: Monitor | E14: 5190626 | F14: 0.07 | G14: 18 | H14: Consumer | I14: 323779 | J14: 14 | K14: =VLOOKUP(D14,LookupTable!$B$2:$C$11,2,FALSE) -> Technology | L14: =VLOOKUP(D14,LookupTable!$B$2:$G$11,6,FALSE) -> Warehouse 1 | M14: =HLOOKUP(D14,LookupTable!$A$15:$K$19,4,FALSE) -> 12 | O14: =INDEX(LookupTable!$D$2:$D$11,MATCH(Lookup!D14,LookupTable!$B$2:$B$11,0)) -> Supplier A
... A31: 1030 | B31: Charlie Brown | C31: South | D31: Chair | E31: 1622550 | F31: 0.15 | G31: 14 | H31: Consumer | I31: 414403 | J31: 3 | K31: =VLOOKUP(D31,LookupTable!$B$2:$C$11,2,FALSE) -> Furniture | L31: =VLOOKUP(D31,LookupTable!$B$2:$G$11,6,FALSE) -> Warehouse 2 | M31: =HLOOKUP(D31,LookupTable!$A$15:$K$19,4,FALSE) -> 60 | O31: =INDEX(LookupTable!$D$2:$D$11,MATCH(Lookup!D31,LookupTable!$B$2:$B$11,0)) -> Supplier E

Sheet LookupTable
A1: Prod ID | B1: Product Name | C1: Category | D1: Supplier | E1: Stock Available | F1: Reorder Level | G1: Warehouse Location
A2: P001 | B2: Laptop | C2: Technology | D2: Supplier A | E2: 50 | F2: 10 | G2: Warehouse 1
A3: P002 | B3: Smartphone | C3: Technology | D3: Supplier B | E3: 30 | F3: 5 | G3: Warehouse 2
A4: P003 | B4: Tablet | C4: Technology | D4: Supplier C | E4: 20 | F4: 8 | G4: Warehouse 3
A5: P004 | B5: Headphones | C5: Accessories | D5: Supplier D | E5: 100 | F5: 30 | G5: Warehouse 4
A6: P005 | B6: Monitor | C6: Technology | D6: Supplier A | E6: 15 | F6: 5 | G6: Warehouse 1
A7: P006 | B7: Chair | C7: Furniture | D7: Supplier E | E7: 80 | F7: 20 | G7: Warehouse 2
A8: P007 | B8: Desk | C8: Furniture | D8: Supplier F | E8: 40 | F8: 10 | G8: Warehouse 3
A9: P008 | B9: Printer | C9: Technology | D9: Supplier G | E9: 12 | F9: 5 | G9: Warehouse 4
A10: P009 | B10: Camera | C10: Electronics | D10: Supplier H | E10: 10 | F10: 3 | G10: Warehouse 1
A11: P010 | B11: Mouse | C11: Accessories | D11: Supplier I | E11: 150 | F11: 50 | G11: Warehouse 2
A15: Product | B15: Laptop | C15: Mouse | D15: Printer | E15: Tablet | F15: Camera | G15: Headphones | H15: Monitor | I15: Desk | J15: Chair | K15: Smartphone
A16: Category | B16: Tech | C16: Acc | D16: Tech | E16: Tech | F16: Elec | G16: Acc | H16: Tech | I16: Furn | J16: Furn | K16: Tech
A17: Supplier | B17: SupA | C17: SupB | D17: SupC | E17: SupD | F17: SupE | G17: SupF | H17: SupG | I17: SupH | J17: SupI | K17: SupJ
A18: Stock Available | B18: 50 | C18: 150 | D18: 20 | E18: 30 | F18: 10 | G18: 80 | H18: 12 | I18: 40 | J18: 60 | K18: 30
A19: Reorder Level | B19: 10 | C19: 50 | D19: 8 | E19: 10 | F19: 3 | G19: 20 | H19: 5 | I19: 10 | J19: 15 | K19: 5

Sheet Cleaning
A1: Name | B1: Email | C1: Phone Number | D1: Address | E1: Country
A2: alice JOHNSON | B2: ALICE@GOOGLE.COM | C2: (123) 4567890 | D2: 123 Main St, City A | E2: USA
A3: BOB martin | B3: BOB@YAHOO.com | C3: (987) 6543210 | D3: 456 Elm St, City B | E3: UK
A4: charlie brown | B4: charlie@yahoo.COM | C4: 1234567890 | D4: 789 Oak St, City C | E4: Canada
A5: dave WHITE | B5: DAVE@google.com | C5: (555) 5555555 | D5: 101 Pine St, City D | E5: Australia
A6: EVE SMITH | B6: eve@google.com | C6: 9998887777 | D6: 222 Maple St, City E | E6: Germany
A8: Name (PROPER) | B8: Email (LOWER) | C8: Phone Number | D8: Address (TRIM) | E8: Country (Upper) | F8: Spasi | G8: Nama Depan (Left+Find) | H8: Nama Depan | I8: LEN | J8: Nama Belakang (Pakai Helper) | K8: Nama Belakang (RIGHT)
A9: =PROPER(A2) -> Alice Johnson | B9: =LOWER(B2) -> alice@google.com | C9: =SUBSTITUTE(C2,"-","") -> (123) 4567890 | D9: =TRIM(D2) -> 123 Main St, City A | E9: =UPPER(E2) -> USA | F9: =FIND(" ",A9) -> 6 | G9: =LEFT(A9,FIND(" ",A9,1)-1) -> Alice | H9: =LEFT(A9,F9) -> Alice | I9: =LEN(A9) -> 13 | J9: =RIGHT(A9,I9-F9) -> Johnson | K9: =RIGHT(A9,LEN(A9)-FIND(" ",A9,1)) -> Johnson
A10: =PROPER(A3) -> Bob Martin | B10: =LOWER(B3) -> bob@yahoo.com | D10: =TRIM(D3) -> 456 Elm St, City B | E10: =UPPER(E3) -> UK | F10: =FIND(" ",A10) -> 4 | G10: =LEFT(A10,FIND(" ",A10,1)-1) -> Bob | H10: =LEFT(A10,F10) -> Bob | I10: =LEN(A10) -> 10 | J10: =RIGHT(A10,I10-F10) -> Martin | K10: =RIGHT(A10,LEN(A10)-FIND(" ",A10,1)) -> Martin
A11: =PROPER(A4) -> Charlie Brown | B11: =LOWER(B4) -> charlie@yahoo.com | D11: =TRIM(D4) -> 789 Oak St, City C | E11: =UPPER(E4) -> CANADA | F11: =FIND(" ",A11) -> 8 | G11: =LEFT(A11,FIND(" ",A11,1)-1) -> Charlie | H11: =LEFT(A11,F11) -> Charlie | I11: =LEN(A11) -> 13 | J11: =RIGHT(A11,I11-F11) -> Brown | K11: =RIGHT(A11,LEN(A11)-FIND(" ",A11,1)) -> Brown
A12: =PROPER(A5) -> Dave White | B12: =LOWER(B5) -> dave@google.com | D12: =TRIM(D5) -> 101 Pine St, City D | E12: =UPPER(E5) -> AUSTRALIA | F12: =FIND(" ",A12) -> 5 | G12: =LEFT(A12,FIND(" ",A12,1)-1) -> Dave | H12: =LEFT(A12,F12) -> Dave | I12: =LEN(A12) -> 10 | J12: =RIGHT(A12,I12-F12) -> White | K12: =RIGHT(A12,LEN(A12)-FIND(" ",A12,1)) -> White
A13: =PROPER(A6) -> Eve Smith | B13: =LOWER(B6) -> eve@google.com | D13: =TRIM(D6) -> 222 Maple St, City E | E13: =UPPER(E6) -> GERMANY | F13: =FIND(" ",A13) -> 4 | G13: =LEFT(A13,FIND(" ",A13,1)-1) -> Eve | H13: =LEFT(A13,F13) -> Eve | I13: =LEN(A13) -> 9 | J13: =RIGHT(A13,I13-F13) -> Smith | K13: =RIGHT(A13,LEN(A13)-FIND(" ",A13,1)) -> Smith
F14: Asta Rabiulardan Hatta
F15: Spasi 1 | G15: Spasi 2 | H15: LEN | I15: Len
A16: Asta Rabiulardan Hatta | F16: =FIND(" ",F14) -> 5 | G16: =FIND(" ",F14,6) -> 17 | H16: =LEN(F14) -> 22 | I16: =LEN(A16) -> 22 | J16: =RIGHT(A16,I16-F16) -> Rabiulardan Hatta | K16: =RIGHT(A16,LEN(A16)-FIND(" ",A16,1)) -> Rabiulardan Hatta
A18: Cleaning Data | F18: =MID(F14,F16+1,H16-G16) -> Rabiu
A19: 1. Cleaning Name menggunakan =PROPER
A20: 2. Cleaning Email menngunakan =LOWER
A21: 3. Cleaning "Phone Number" (Menggunakan SUBSTITUTE)
A22: =SUBSTITUTE(SUBSTITUTE(SUBSTITUTE(C2, "(", ""), ")", ""), "-", "")
A23: 4. Cleaning "Address" (Menggunakan TRIM)
A26: Extract Nama Depan dan Belakang
A27: 1. Temukan Posisi Spasi dalam Nama menggunakan FIND
A28: 2. Extract Nama Depan menggunakan LEFT dan FIND
A29: 3. Extract Nama Belakang Menggunakan RIGHT dan LEN
A30: 4. Penggunaan MID untuk mengekstrak nama Tengah, coba contoh dibawah

Sheet Sales Data
A1: Order ID | B1: Sales Name | C1: Region | D1: Product | E1: Unit Price | F1: Discount | G1: Unit Price After Discount | H1: Quantity | I1: Total Sales | J1: Customer Segment | K1: Shipping Cost | L1: Amount to Pay | M1: Delivery Time (Days) | N1: Category | O1: Supplier | P1: Stock Available | Q1: Reorder Level | R1: Warehouse Location
A2: 1001 | B2: Bob Martin | C2: North | D2: Laptop | E2: 4612059 | F2: 0.1 | H2: 20 | J2: Corporate | K2: 327163 | M2: 2
A3: 1002 | B3: Bob Martin | C3: North | D3: Mouse | E3: 415612 | F3: 0.17 | H3: 1 | J3: Consumer | K3: 783312 | M3: 7
A4: 1003 | B4: David White | C4: East | D4: Printer | E4: 1725042 | F4: 0.2 | H4: 17 | J4: Small Business | K4: 573976 | M4: 7
A5: 1004 | B5: Bob Martin | C5: East | D5: Laptop | E5: 32495820 | F5: 0.19 | H5: 12 | J5: Small Business | K5: 715388 | M5: 8
A6: 1005 | B6: Eve Smith | C6: West | D6: Headphones | E6: 381259 | F6: 0.08 | H6: 9 | J6: Consumer | K6: 516373 | M6: 1
A7: 1006 | B7: Bob Martin | C7: South | D7: Tablet | E7: 3517798 | F7: 0.08 | H7: 5 | J7: Corporate | K7: 488560 | M7: 4
A8: 1007 | B8: Bob Martin | C8: East | D8: Printer | E8: 4056860 | F8: 0.14 | H8: 9 | J8: Corporate | K8: 541297 | M8: 6
A9: 1008 | B9: David White | C9: East | D9: Smartphone | E9: 9154155 | F9: 0.2 | H9: 12 | J9: Consumer | K9: 568288 | M9: 7
A10: 1009 | B10: Alice Johnson | C10: East | D10: Camera | E10: 4734466 | F10: 0.16 | H10: 16 | J10: Consumer | K10: 652076 | M10: 13
A11: 1010 | B11: Charlie Brown | C11: East | D11: Headphones | E11: 235319 | F11: 0.14 | H11: 20 | J11: Corporate | K11: 394800 | M11: 2
A12: 1011 | B12: Alice Johnson | C12: West | D12: Tablet | E12: 14931496 | F12: 0.11 | H12: 14 | J12: Small Business | K12: 660012 | M12: 4
A13: 1012 | B13: Charlie Brown | C13: West | D13: Headphones | E13: 265689 | F13: 0.08 | H13: 9 | J13: Small Business | K13: 609492 | M13: 3
... A201: 1200 | B201: Bob Martin | C201: North | D201: Printer | E201: 7520281 | F201: 0.06 | H201: 3 | J201: Consumer | K201: 458599 | M201: 4
